get_result/__init__.py
get_result/get_result.py
get_result/lerccodec.py
get_result/resultconverter.py
get_result/vrtconverter.py
get_result/zarrconverter.py
s11_get_result-0.0.33.dist-info/METADATA
s11_get_result-0.0.33.dist-info/WHEEL
s11_get_result-0.0.33.dist-info/entry_points.txt
s11_get_result-0.0.33.dist-info/top_level.txt
s11_get_result-0.0.33.dist-info/RECORD
