Metadata-Version: 2.4
Name: s11-get-result
Version: 0.0.33
Summary: Tool to download Satelligence raster data from Google Cloud Storage.
Author-email: Satelligence <schut@satelligence.com>
License: Apache-2.0
Classifier: Programming Language :: Python :: 3
Classifier: License :: OSI Approved :: Apache Software License
Classifier: Operating System :: OS Independent
Requires-Python: >=3.12
Requires-Dist: cyclopts==3.16.0
Requires-Dist: gcsfs>=2024.6.1
Requires-Dist: pylerc>=4.0
Requires-Dist: numcodecs>=0.13.1
Requires-Dist: numpy>=1.20.0
Requires-Dist: tqdm<5.0.0,>=4.64.0
Requires-Dist: pebble<6.0.0,>=5.0.0
Requires-Dist: rioxarray>=0.18.0
Requires-Dist: xarray>=2024.1.0
Requires-Dist: zarr<3.0.0,>=2.18.3
